MANIFEST.in
setup.py
baby_browser/__init__.py
baby_browser/baby_browser.py
baby_browser/menu_objects.py
baby_browser/assets/css/browser.css
baby_browser/assets/fonts/Quicksand-Regular.otf
baby_browser/assets/fonts/fontawesome-webfont.ttf
baby_browser/assets/fonts/raleway/Raleway-Black.ttf
baby_browser/assets/fonts/raleway/Raleway-BlackItalic.ttf
baby_browser/assets/fonts/raleway/Raleway-Bold.ttf
baby_browser/assets/fonts/raleway/Raleway-BoldItalic.ttf
baby_browser/assets/fonts/raleway/Raleway-ExtraBold.ttf
baby_browser/assets/fonts/raleway/Raleway-ExtraBoldItalic.ttf
baby_browser/assets/fonts/raleway/Raleway-ExtraLight.ttf
baby_browser/assets/fonts/raleway/Raleway-ExtraLightItalic.ttf
baby_browser/assets/fonts/raleway/Raleway-Italic.ttf
baby_browser/assets/fonts/raleway/Raleway-Light.ttf
baby_browser/assets/fonts/raleway/Raleway-LightItalic.ttf
baby_browser/assets/fonts/raleway/Raleway-Medium.ttf
baby_browser/assets/fonts/raleway/Raleway-MediumItalic.ttf
baby_browser/assets/fonts/raleway/Raleway-Regular.ttf
baby_browser/assets/fonts/raleway/Raleway-SemiBold.ttf
baby_browser/assets/fonts/raleway/Raleway-SemiBoldItalic.ttf
baby_browser/assets/fonts/raleway/Raleway-Thin.ttf
baby_browser/assets/fonts/raleway/Raleway-ThinItalic.ttf
baby_browser/assets/fonts/raleway/SIL Open Font License.txt
baby_browser/assets/images/back.png
baby_browser/assets/images/bookmark.png
baby_browser/assets/images/bookmark_border.png
baby_browser/assets/images/close.png
baby_browser/assets/images/crib.png
baby_browser/assets/images/crib_background.png
baby_browser/assets/images/crib_white.png
baby_browser/assets/images/fav-border.png
baby_browser/assets/images/fav-full.png
baby_browser/assets/images/favicon-plus-square.ico
baby_browser/assets/images/favicon-tint.ico
baby_browser/assets/images/forward.png
baby_browser/assets/images/new folder black.png
baby_browser/assets/images/new folder.png
baby_browser/assets/images/page.png
baby_browser/assets/images/plus.png
babybrowser.egg-info/PKG-INFO
babybrowser.egg-info/SOURCES.txt
babybrowser.egg-info/dependency_links.txt
babybrowser.egg-info/entry_points.txt
babybrowser.egg-info/not-zip-safe
babybrowser.egg-info/requires.txt
babybrowser.egg-info/top_level.txt