Metadata-Version: 1.0
Name: babybrowser
Version: 0.1.1
Summary: A small browser implementation in Python
Home-page: https://github.com/lauryndbrown/BabyBrowser
Author: Lauryn Brown
Author-email: lauryndbrown@gmail.com
License: GNU GPLv3
Platform: UNKNOWN
